[{"model":"Llama-2-13b-hf_attack_results.csv","seed":42.0,"clean_acc":0.7472924188,"attack_acc":0.4657039711,"asr":0.3797885121},{"model":"Llama-2-7b-hf_attack_results.csv","seed":42.0,"clean_acc":0.7172081829,"attack_acc":0.5992779783,"asr":0.1643244367},{"model":"Mistral-7B-v0.1_attack_results.csv","seed":42.0,"clean_acc":0.7761732852,"attack_acc":0.6209386282,"asr":0.2000930521},{"model":"Mixtral-8x7B-v0.1_attack_results.csv","seed":42.0,"clean_acc":0.7749699158,"attack_acc":0.6474127557,"asr":0.1646849416},{"model":"gemma-7b_attack_results.csv","seed":42.0,"clean_acc":0.7641395909,"attack_acc":0.5559566787,"asr":0.2739902159},{"model":"vicuna-7b-v1.5_attack_results.csv","seed":42.0,"clean_acc":0.7725631769,"attack_acc":0.7268351384,"asr":0.0591545554}]